nummer_games/Classifygeneration.py
nummer_games/Genericgeneration.py
nummer_games/Primegeneration.py
nummer_games/__init__.py
nummer_games-0.2.dist-info/METADATA
nummer_games-0.2.dist-info/WHEEL
nummer_games-0.2.dist-info/top_level.txt
nummer_games-0.2.dist-info/RECORD
