Metadata-Version: 2.1
Name: nummer-games
Version: 0.2
Summary: Guess random numbers and prime numbers
Home-page: https://github.com/imisi-akande/number-game
Author: Akande Imisioluwa
Author-email: imizezek84@gmail.com
License: UNKNOWN
Platform: UNKNOWN
Classifier: Programming Language :: Python :: 3
Classifier: License :: OSI Approved :: MIT License
Classifier: Operating System :: OS Independent
Requires-Python: >=3.6
